LICENSE.txt
MANIFEST.in
PyPeLoader.py
README.md
pyproject.toml
setup.cfg
setup.py
PyPeLoader.egg-info/PKG-INFO
PyPeLoader.egg-info/SOURCES.txt
PyPeLoader.egg-info/dependency_links.txt
PyPeLoader.egg-info/entry_points.txt
PyPeLoader.egg-info/top_level.txt